tap/__init__.py
tap/__main__.py
tap/adapter.py
tap/directive.py
tap/formatter.py
tap/line.py
tap/loader.py
tap/main.py
tap/parser.py
tap/rules.py
tap/runner.py
tap/tracker.py
tap/tests/__init__.py
tap/tests/factory.py
tap/tests/test_example.py
tap/tests/testcase.py
tap_py-3.2.1.dist-info/METADATA
tap_py-3.2.1.dist-info/WHEEL
tap_py-3.2.1.dist-info/entry_points.txt
tap_py-3.2.1.dist-info/licenses/AUTHORS
tap_py-3.2.1.dist-info/licenses/LICENSE
tap_py-3.2.1.dist-info/RECORD
