Metadata-Version: 2.4
Name: tap.py
Version: 3.2.1
Summary: Test Anything Protocol (TAP) tools
Author-email: Matt Layman <matthewlayman@gmail.com>
License: BSD
License-File: AUTHORS
License-File: LICENSE
Keywords: TAP,unittest
Classifier: Development Status :: 5 - Production/Stable
Classifier: Environment :: Console
Classifier: Intended Audience :: Developers
Classifier: License :: OSI Approved :: BSD License
Classifier: Operating System :: OS Independent
Classifier: Programming Language :: Python :: 3.9
Classifier: Programming Language :: Python :: 3.10
Classifier: Programming Language :: Python :: 3.11
Classifier: Programming Language :: Python :: 3.12
Classifier: Programming Language :: Python :: 3.13
Classifier: Topic :: Software Development :: Testing
Requires-Python: >=3.9
Provides-Extra: yaml
Requires-Dist: more-itertools; extra == 'yaml'
Requires-Dist: pyyaml>=5.1; extra == 'yaml'
